haram_sub/__init__.py
haram_sub/sub.py
haram_sub-0.1.3.dist-info/METADATA
haram_sub-0.1.3.dist-info/WHEEL
haram_sub-0.1.3.dist-info/entry_points.txt
haram_sub-0.1.3.dist-info/top_level.txt
haram_sub-0.1.3.dist-info/RECORD
