Metadata-Version: 2.1
Name: haram_sub
Version: 0.1.3
Summary: Default template for PDM package
Author-email: HaramSs <haram8274@gmail.com>
License: MIT
Requires-Python: >=3.9
